newsprofile/NewsprofileService_pb2.py
newsprofile/NewsprofileService_pb2_grpc.py
newsprofile/__init__.py
newsprofile/newsprofile_channel_pool.py
newsprofile/newsprofile_grpc_client.py
src/NewsprofileService_pb2.py
src/NewsprofileService_pb2_grpc.py
src/__init__.py
src/newsprofile_channel_pool.py
src/newsprofile_grpc_client.py
newsprofile-1.0.0.dist-info/METADATA
newsprofile-1.0.0.dist-info/WHEEL
newsprofile-1.0.0.dist-info/top_level.txt
newsprofile-1.0.0.dist-info/RECORD
