Metadata-Version: 2.1
Name: newsprofile
Version: 1.0.0
Summary: Grpc client for newsprofile
Requires-Dist: grpcio-tools (==1.42.0)
